Metadata-Version: 2.4
Name: mcp-get-weather-agent
Version: 0.1.0
Summary: 输入OpenWeather-API-KEY，获取天气信息
Requires-Python: >=3.12
Requires-Dist: build>=1.2.2.post1
Requires-Dist: dotenv>=0.9.9
Requires-Dist: httpx>=0.28.1
Requires-Dist: mcp>=1.7.1
Requires-Dist: openai>=1.77.0
Requires-Dist: twine>=6.1.0
